Workbook

Sheet Productos Factura FVE150174
A1: Factura FVE150174 - Importadora OKLA S.A.S. — Autopartes Pita (18/09/2026) | L1: Margen de venta sugerido: | M1: 0.4
A3: Item | B3: Referencia | C3: Producto | D3: Cantidad | E3: Precio Unit. sin IVA | F3: % IVA | G3: Precio Unit. con IVA | H3: Valor Total con IVA | I3: Precio Venta Sugerido (Unit., +40%) | J3: Valor Venta Total Sugerido
A4: 1 | B4: CRINF233 | C4: Paso rueda CH Spark GT RH (11-19) TYC | D4: 2 | E4: 39200 | F4: 0.19 | G4: =E4*(1+F4) -> 46648 | H4: =G4*D4 -> 93296 | I4: =G4*(1+$M$1) -> 65307.2 | J4: =I4*D4 -> 130614.4
A5: 2 | B5: CRINF232 | C5: Paso rueda CH Spark GT LH (11-19) TYC | D5: 1 | E5: 39200 | F5: 0.19 | G5: =E5*(1+F5) -> 46648 | H5: =G5*D5 -> 46648 | I5: =G5*(1+$M$1) -> 65307.2 | J5: =I5*D5 -> 65307.2
A6: 3 | B6: CRINF74 | C6: Paso rueda CH Spark Chronos RH (05-14) TYC | D6: 1 | E6: 28800 | F6: 0.19 | G6: =E6*(1+F6) -> 34272 | H6: =G6*D6 -> 34272 | I6: =G6*(1+$M$1) -> 47980.8 | J6: =I6*D6 -> 47980.8
A7: 4 | B7: CRINF75 | C7: Paso rueda CH Spark Chronos LH (05-14) TYC | D7: 2 | E7: 28800 | F7: 0.19 | G7: =E7*(1+F7) -> 34272 | H7: =G7*D7 -> 68544 | I7: =G7*(1+$M$1) -> 47980.8 | J7: =I7*D7 -> 95961.6
A8: 5 | B8: CRINF166 | C8: Paso rueda CH Corsa MV/Wind RH (98-07) TYC | D8: 1 | E8: 23200 | F8: 0.19 | G8: =E8*(1+F8) -> 27608 | H8: =G8*D8 -> 27608 | I8: =G8*(1+$M$1) -> 38651.2 | J8: =I8*D8 -> 38651.2
A9: 6 | B9: CRINF167 | C9: Paso rueda CH Corsa MV/Wind LH (98-07) TYC | D9: 1 | E9: 23200 | F9: 0.19 | G9: =E9*(1+F9) -> 27608 | H9: =G9*D9 -> 27608 | I9: =G9*(1+$M$1) -> 38651.2 | J9: =I9*D9 -> 38651.2
A10: 7 | B10: CRRET36 | C10: Espejo CH Spark GT c/cable LH (10-14) TYC | D10: 1 | E10: 104800 | F10: 0.19 | G10: =E10*(1+F10) -> 124712 | H10: =G10*D10 -> 124712 | I10: =G10*(1+$M$1) -> 174596.8 | J10: =I10*D10 -> 174596.8
A11: 8 | B11: CRRET168 | C11: Espejo CH Spark Chronos manual LH (05-14) TYC | D11: 1 | E11: 72800 | F11: 0.19 | G11: =E11*(1+F11) -> 86632 | H11: =G11*D11 -> 86632 | I11: =G11*(1+$M$1) -> 121284.8 | J11: =I11*D11 -> 121284.8
A12: 9 | B12: CRRET106 | C12: Espejo CH Corsa c/cable RH (96-04) TYC | D12: 1 | E12: 31200 | F12: 0.19 | G12: =E12*(1+F12) -> 37128 | H12: =G12*D12 -> 37128 | I12: =G12*(1+$M$1) -> 51979.2 | J12: =I12*D12 -> 51979.2
A13: 10 | B13: CRRET107 | C13: Espejo CH Corsa c/cable LH (96-04) TYC | D13: 1 | E13: 31200 | F13: 0.19 | G13: =E13*(1+F13) -> 37128 | H13: =G13*D13 -> 37128 | I13: =G13*(1+$M$1) -> 51979.2 | J13: =I13*D13 -> 51979.2
A14: 11 | B14: CRSIL10 | C14: Lámpara guardabarro HY Atos LH-RH (05-12) Todo | D14: 6 | E14: 5600 | F14: 0.19 | G14: =E14*(1+F14) -> 6664 | H14: =G14*D14 -> 39984 | I14: =G14*(1+$M$1) -> 9329.6 | J14: =I14*D14 -> 55977.6
A15: 12 | B15: CRSIL33 | C15: Lámpara guardabarro CH Spark Chronos c/u LH-RH (05-14) Todo | D15: 6 | E15: 5600 | F15: 0.19 | G15: =E15*(1+F15) -> 6664 | H15: =G15*D15 -> 39984 | I15: =G15*(1+$M$1) -> 9329.6 | J15: =I15*D15 -> 55977.6
... A26: 23 | B26: CRREB51 | C26: Bomper trasero HY Grand i10 HB (15-18) FPI | D26: 1 | E26: 165830 | F26: 0.19 | G26: =E26*(1+F26) -> 197337.7 | H26: =G26*D26 -> 197337.7 | I26: =G26*(1+$M$1) -> 276272.78 | J26: =I26*D26 -> 276272.78
C27: TOTALES | D27: =SUM(D4:D26) -> 52 | H27: =SUM(H4:H26) -> 1832873.7 | J27: =SUM(J4:J26) -> 2566023.2
A29: Nota: 'Precio Unit. sin IVA' y 'Valor Total con IVA' se calculan a partir de los precios con descuento de la factura (no incluyen el flete de $44,830 ni la retefuente, que la factura prorratea aparte). El precio de venta sugerido aplica el margen del 40% (celda amarilla M1, editable) sobre el costo unitario con IVA incluido. No fue posible verificar precios de mercado confiables para estas referencias específicas de importador (códigos internos TYC/Todo/OKLA); si tienes referencias equivalentes de la competencia, con gusto las comparo.

Sheet Registro Ventas y Ganancias
A1: Registro de Ventas y Ganancias
A2: Llena solo las celdas amarillas (Fecha, Referencia, Cantidad Vendida, Precio Venta Unitario). El Producto y el Costo se traen solos de la hoja de la factura, y la Ganancia se calcula sola.
A4: Fecha | B4: Referencia | C4: Producto | D4: Costo Unit. (con IVA) | E4: Cantidad Vendida | F4: Precio Venta Unitario | G4: Valor Venta Total | H4: Costo Total | I4: Ganancia | J4: Margen
A5: 46286 | B5: CRFRB29 | C5: Bomper delantero CH Spark GT (11-14) Todo | D5: =IFERROR(_xlfn.XLOOKUP(Tabla2[[#This Row],[Referencia]], Tabla1[Referencia], Tabla1[Precio Unit. con IVA]), "0") -> 189448 | E5: 1 | F5: 300000 | G5: 300000 | H5: =IF(AND(D5<>"",E5<>""),D5*E5,"") -> 189448 | I5: =IF(AND(G5<>"",H5<>""),G5-H5,"") -> 110552 | J5: =Tabla2[[#This Row],[Ganancia]]/2 -> 55276
A6: 46286 | B6: CRREB51 | C6: Bomper trasero HY Grand i10 HB (15-18) FPI | D6: =IFERROR(_xlfn.XLOOKUP(Tabla2[[#This Row],[Referencia]], Tabla1[Referencia], Tabla1[Precio Unit. con IVA]), "0") -> 197337.7 | E6: 1 | F6: 250000 | G6: =IF(AND(E6<>"",F6<>""),E6*F6,"") -> 250000 | H6: =IF(AND(D6<>"",E6<>""),D6*E6,"") -> 197337.7 | I6: =IF(AND(G6<>"",H6<>""),G6-H6,"") -> 52662.3 | J6: =Tabla2[[#This Row],[Ganancia]]/2 -> 26331.15
A7: 46291 | B7: CRINF166 | C7: Paso rueda CH Corsa MV/Wind RH (98-07) TYC | D7: =IFERROR(_xlfn.XLOOKUP(Tabla2[[#This Row],[Referencia]], Tabla1[Referencia], Tabla1[Precio Unit. con IVA]), "0") -> 27608 | E7: 1 | F7: 35000 | G7: =IF(AND(E7<>"",F7<>""),E7*F7,"") -> 35000 | H7: =IF(AND(D7<>"",E7<>""),D7*E7,"") -> 27608 | I7: =IF(AND(G7<>"",H7<>""),G7-H7,"") -> 7392 | J7: =Tabla2[[#This Row],[Ganancia]]/2 -> 3696
A8: 46292 | B8: CRINF167 | C8: Paso rueda CH Corsa MV/Wind LH (98-07) TYC | D8: =IFERROR(_xlfn.XLOOKUP(Tabla2[[#This Row],[Referencia]], Tabla1[Referencia], Tabla1[Precio Unit. con IVA]), "0") -> 27608 | E8: 1 | F8: 35000 | G8: =IF(AND(E8<>"",F8<>""),E8*F8,"") -> 35000 | H8: =IF(AND(D8<>"",E8<>""),D8*E8,"") -> 27608 | I8: =IF(AND(G8<>"",H8<>""),G8-H8,"") -> 7392 | J8: =Tabla2[[#This Row],[Ganancia]]/2 -> 3696
A9: 46293 | B9: CRELC266 | C9: Flasher direccional CH Chronos/Sail/Optra/Spark/Aveo/DW | D9: =IFERROR(_xlfn.XLOOKUP(Tabla2[[#This Row],[Referencia]], Tabla1[Referencia], Tabla1[Precio Unit. con IVA]), "0") -> 5712 | E9: 1 | F9: 15000 | G9: =IF(AND(E9<>"",F9<>""),E9*F9,"") -> 15000 | H9: =IF(AND(D9<>"",E9<>""),D9*E9,"") -> 5712 | I9: =IF(AND(G9<>"",H9<>""),G9-H9,"") -> 9288 | J9: =Tabla2[[#This Row],[Ganancia]]/2 -> 4644
A10: 46297 | B10: CRREB14 | C10: Bomper trasero CH Sail (12-20) Todo | D10: =IFERROR(_xlfn.XLOOKUP(Tabla2[[#This Row],[Referencia]], Tabla1[Referencia], Tabla1[Precio Unit. con IVA]), "0") -> 125664 | E10: 1 | F10: 200000 | G10: =IF(AND(E10<>"",F10<>""),E10*F10,"") -> 200000 | H10: =IF(AND(D10<>"",E10<>""),D10*E10,"") -> 125664 | I10: =IF(AND(G10<>"",H10<>""),G10-H10,"") -> 74336 | J10: =Tabla2[[#This Row],[Ganancia]]/2 -> 37168
A11: 46301 | B11: CRELC149 | C11: Switch parqueo HY Atos/Machage | D11: =IFERROR(_xlfn.XLOOKUP(Tabla2[[#This Row],[Referencia]], Tabla1[Referencia], Tabla1[Precio Unit. con IVA]), "0") -> 12376 | E11: 1 | F11: 30000 | G11: =IF(AND(E11<>"",F11<>""),E11*F11,"") -> 30000 | H11: =IF(AND(D11<>"",E11<>""),D11*E11,"") -> 12376 | I11: =IF(AND(G11<>"",H11<>""),G11-H11,"") -> 17624 | J11: =Tabla2[[#This Row],[Ganancia]]/2 -> 8812
A12: 46301 | B12: CRFRB12 | C12: Bomper delantero CH Spark Chronos (05-14) Todo | D12: =IFERROR(_xlfn.XLOOKUP(Tabla2[[#This Row],[Referencia]], Tabla1[Referencia], Tabla1[Precio Unit. con IVA]), "0") -> 93296 | E12: 1 | F12: 170000 | G12: =IF(AND(E12<>"",F12<>""),E12*F12,"") -> 170000 | H12: =IF(AND(D12<>"",E12<>""),D12*E12,"") -> 93296 | I12: =IF(AND(G12<>"",H12<>""),G12-H12,"") -> 76704 | J12: =Tabla2[[#This Row],[Ganancia]]/2 -> 38352
C13: =IFERROR(INDEX('Productos Factura FVE150174'!$C$4:$C$26,MATCH(B13,'Productos Factura FVE150174'!$B$4:$B$26,0)),"") | D13: =IFERROR(_xlfn.XLOOKUP(Tabla2[[#This Row],[Referencia]], Tabla1[Referencia], Tabla1[Precio Unit. con IVA]), "0") -> 0 | E13: 0 | F13: =Tabla2[[#This Row],[Cantidad Vendida]]*Tabla2[[#This Row],[Costo Unit. (con IVA)]] -> 0 | G13: =IF(AND(E13<>"",F13<>""),E13*F13,"") -> 0 | H13: =IF(AND(D13<>"",E13<>""),D13*E13,"") -> 0 | I13: 0 | J13: =Tabla2[[#This Row],[Ganancia]]/2 -> 0
C14: =IFERROR(INDEX('Productos Factura FVE150174'!$C$4:$C$26,MATCH(B14,'Productos Factura FVE150174'!$B$4:$B$26,0)),"") | D14: =IFERROR(_xlfn.XLOOKUP(Tabla2[[#This Row],[Referencia]], Tabla1[Referencia], Tabla1[Precio Unit. con IVA]), "0") -> 0 | E14: 0 | F14: =Tabla2[[#This Row],[Cantidad Vendida]]*Tabla2[[#This Row],[Costo Unit. (con IVA)]] -> 0 | G14: =IF(AND(E14<>"",F14<>""),E14*F14,"") -> 0 | H14: =IF(AND(D14<>"",E14<>""),D14*E14,"") -> 0 | I14: 0 | J14: =Tabla2[[#This Row],[Ganancia]]/2 -> 0
C15: =IFERROR(INDEX('Productos Factura FVE150174'!$C$4:$C$26,MATCH(B15,'Productos Factura FVE150174'!$B$4:$B$26,0)),"") | D15: =IFERROR(_xlfn.XLOOKUP(Tabla2[[#This Row],[Referencia]], Tabla1[Referencia], Tabla1[Precio Unit. con IVA]), "0") -> 0 | E15: 0 | F15: =Tabla2[[#This Row],[Cantidad Vendida]]*Tabla2[[#This Row],[Costo Unit. (con IVA)]] -> 0 | G15: =IF(AND(E15<>"",F15<>""),E15*F15,"") -> 0 | H15: =IF(AND(D15<>"",E15<>""),D15*E15,"") -> 0 | I15: 0 | J15: =Tabla2[[#This Row],[Ganancia]]/2 -> 0
C16: =IFERROR(INDEX('Productos Factura FVE150174'!$C$4:$C$26,MATCH(B16,'Productos Factura FVE150174'!$B$4:$B$26,0)),"") | D16: =IFERROR(_xlfn.XLOOKUP(Tabla2[[#This Row],[Referencia]], Tabla1[Referencia], Tabla1[Precio Unit. con IVA]), "0") -> 0 | E16: 0 | F16: =Tabla2[[#This Row],[Cantidad Vendida]]*Tabla2[[#This Row],[Costo Unit. (con IVA)]] -> 0 | G16: =IF(AND(E16<>"",F16<>""),E16*F16,"") -> 0 | H16: =IF(AND(D16<>"",E16<>""),D16*E16,"") -> 0 | I16: 0 | J16: =Tabla2[[#This Row],[Ganancia]]/2 -> 0
C17: =IFERROR(INDEX('Productos Factura FVE150174'!$C$4:$C$26,MATCH(B17,'Productos Factura FVE150174'!$B$4:$B$26,0)),"") | D17: =IFERROR(_xlfn.XLOOKUP(Tabla2[[#This Row],[Referencia]], Tabla1[Referencia], Tabla1[Precio Unit. con IVA]), "0") -> 0 | E17: 0 | F17: =Tabla2[[#This Row],[Cantidad Vendida]]*Tabla2[[#This Row],[Costo Unit. (con IVA)]] -> 0 | G17: =IF(AND(E17<>"",F17<>""),E17*F17,"") -> 0 | H17: =IF(AND(D17<>"",E17<>""),D17*E17,"") -> 0 | I17: 0 | J17: =Tabla2[[#This Row],[Ganancia]]/2 -> 0
C18: =IFERROR(INDEX('Productos Factura FVE150174'!$C$4:$C$26,MATCH(B18,'Productos Factura FVE150174'!$B$4:$B$26,0)),"") | D18: =IFERROR(_xlfn.XLOOKUP(Tabla2[[#This Row],[Referencia]], Tabla1[Referencia], Tabla1[Precio Unit. con IVA]), "0") -> 0 | E18: 0 | F18: =Tabla2[[#This Row],[Cantidad Vendida]]*Tabla2[[#This Row],[Costo Unit. (con IVA)]] -> 0 | G18: =IF(AND(E18<>"",F18<>""),E18*F18,"") -> 0 | H18: =IF(AND(D18<>"",E18<>""),D18*E18,"") -> 0 | I18: 0 | J18: =Tabla2[[#This Row],[Ganancia]]/2 -> 0
C19: =IFERROR(INDEX('Productos Factura FVE150174'!$C$4:$C$26,MATCH(B19,'Productos Factura FVE150174'!$B$4:$B$26,0)),"") | D19: =IFERROR(_xlfn.XLOOKUP(Tabla2[[#This Row],[Referencia]], Tabla1[Referencia], Tabla1[Precio Unit. con IVA]), "0") -> 0 | E19: 0 | F19: =Tabla2[[#This Row],[Cantidad Vendida]]*Tabla2[[#This Row],[Costo Unit. (con IVA)]] -> 0 | G19: =IF(AND(E19<>"",F19<>""),E19*F19,"") -> 0 | H19: =IF(AND(D19<>"",E19<>""),D19*E19,"") -> 0 | I19: 0 | J19: =Tabla2[[#This Row],[Ganancia]]/2 -> 0
C20: =IFERROR(INDEX('Productos Factura FVE150174'!$C$4:$C$26,MATCH(B20,'Productos Factura FVE150174'!$B$4:$B$26,0)),"") | D20: =IFERROR(_xlfn.XLOOKUP(Tabla2[[#This Row],[Referencia]], Tabla1[Referencia], Tabla1[Precio Unit. con IVA]), "0") -> 0 | E20: 0 | F20: =Tabla2[[#This Row],[Cantidad Vendida]]*Tabla2[[#This Row],[Costo Unit. (con IVA)]] -> 0 | G20: =IF(AND(E20<>"",F20<>""),E20*F20,"") -> 0 | H20: =IF(AND(D20<>"",E20<>""),D20*E20,"") -> 0 | I20: 0 | J20: =Tabla2[[#This Row],[Ganancia]]/2 -> 0
C21: =IFERROR(INDEX('Productos Factura FVE150174'!$C$4:$C$26,MATCH(B21,'Productos Factura FVE150174'!$B$4:$B$26,0)),"") | D21: =IFERROR(_xlfn.XLOOKUP(Tabla2[[#This Row],[Referencia]], Tabla1[Referencia], Tabla1[Precio Unit. con IVA]), "0") -> 0 | E21: 0 | F21: =Tabla2[[#This Row],[Cantidad Vendida]]*Tabla2[[#This Row],[Costo Unit. (con IVA)]] -> 0 | G21: =IF(AND(E21<>"",F21<>""),E21*F21,"") -> 0 | H21: =IF(AND(D21<>"",E21<>""),D21*E21,"") -> 0 | I21: 0 | J21: =Tabla2[[#This Row],[Ganancia]]/2 -> 0
C22: TOTALES | D22: =SUM(D5:D21) -> 679049.7 | E22: =SUM(E5:E21) -> 8 | G22: =SUM(G5:G21) -> 1035000 | H22: =SUM(H5:H21) -> 679049.7 | I22: =SUM(I5:I21) -> 355950.3 | J22: =SUM(Tabla2[[Margen ]]) -> 177975.15

Sheet Stock
A1: REGISTRO DE LO QUE QUEDA DISPONIBLE (STOCK)
B4: Referencia | C4: Producto | D4: Cantidad | E4: Cantidad Vendida | F4: Cantidad Disponible | G4: Precio Unit. con IVA | H4: Valor Total con IVA
B5: CRINF233 | C5: Paso rueda CH Spark GT RH (11-19) TYC | D5: 2 | E5: =IFERROR(_xlfn.XLOOKUP(Tabla3[[#This Row],[Referencia]], Tabla2[Referencia], Tabla2[Cantidad Vendida]), "0") -> 0 | F5: =Tabla3[[#This Row],[Cantidad]]-Tabla3[[#This Row],[Cantidad Vendida]] -> 2 | G5: =_xlfn.XLOOKUP(Tabla3[[#This Row],[Referencia]],Tabla1[Referencia],Tabla1[Precio Unit. con IVA]) -> 46648 | H5: =Tabla3[[#This Row],[Precio Unit. con IVA]]*Tabla3[[#This Row],[Cantidad Disponible]] -> 93296
B6: CRINF232 | C6: Paso rueda CH Spark GT LH (11-19) TYC | D6: 1 | E6: =IFERROR(_xlfn.XLOOKUP(Tabla3[[#This Row],[Referencia]], Tabla2[Referencia], Tabla2[Cantidad Vendida]), "0") -> 0 | F6: =Tabla3[[#This Row],[Cantidad]]-Tabla3[[#This Row],[Cantidad Vendida]] -> 1 | G6: =_xlfn.XLOOKUP(Tabla3[[#This Row],[Referencia]],Tabla1[Referencia],Tabla1[Precio Unit. con IVA]) -> 46648 | H6: =Tabla3[[#This Row],[Precio Unit. con IVA]]*Tabla3[[#This Row],[Cantidad Disponible]] -> 46648
B7: CRINF74 | C7: Paso rueda CH Spark Chronos RH (05-14) TYC | D7: 1 | E7: =IFERROR(_xlfn.XLOOKUP(Tabla3[[#This Row],[Referencia]], Tabla2[Referencia], Tabla2[Cantidad Vendida]), "0") -> 0 | F7: =Tabla3[[#This Row],[Cantidad]]-Tabla3[[#This Row],[Cantidad Vendida]] -> 1 | G7: =_xlfn.XLOOKUP(Tabla3[[#This Row],[Referencia]],Tabla1[Referencia],Tabla1[Precio Unit. con IVA]) -> 34272 | H7: =Tabla3[[#This Row],[Precio Unit. con IVA]]*Tabla3[[#This Row],[Cantidad Disponible]] -> 34272
B8: CRINF75 | C8: Paso rueda CH Spark Chronos LH (05-14) TYC | D8: 2 | E8: =IFERROR(_xlfn.XLOOKUP(Tabla3[[#This Row],[Referencia]], Tabla2[Referencia], Tabla2[Cantidad Vendida]), "0") -> 0 | F8: =Tabla3[[#This Row],[Cantidad]]-Tabla3[[#This Row],[Cantidad Vendida]] -> 2 | G8: =_xlfn.XLOOKUP(Tabla3[[#This Row],[Referencia]],Tabla1[Referencia],Tabla1[Precio Unit. con IVA]) -> 34272 | H8: =Tabla3[[#This Row],[Precio Unit. con IVA]]*Tabla3[[#This Row],[Cantidad Disponible]] -> 68544
B9: CRINF166 | C9: Paso rueda CH Corsa MV/Wind RH (98-07) TYC | D9: 1 | E9: =IFERROR(_xlfn.XLOOKUP(Tabla3[[#This Row],[Referencia]], Tabla2[Referencia], Tabla2[Cantidad Vendida]), "0") -> 1 | F9: =Tabla3[[#This Row],[Cantidad]]-Tabla3[[#This Row],[Cantidad Vendida]] -> 0 | G9: =_xlfn.XLOOKUP(Tabla3[[#This Row],[Referencia]],Tabla1[Referencia],Tabla1[Precio Unit. con IVA]) -> 27608 | H9: =Tabla3[[#This Row],[Precio Unit. con IVA]]*Tabla3[[#This Row],[Cantidad Disponible]] -> 0
B10: CRINF167 | C10: Paso rueda CH Corsa MV/Wind LH (98-07) TYC | D10: 1 | E10: =IFERROR(_xlfn.XLOOKUP(Tabla3[[#This Row],[Referencia]], Tabla2[Referencia], Tabla2[Cantidad Vendida]), "0") -> 1 | F10: =Tabla3[[#This Row],[Cantidad]]-Tabla3[[#This Row],[Cantidad Vendida]] -> 0 | G10: =_xlfn.XLOOKUP(Tabla3[[#This Row],[Referencia]],Tabla1[Referencia],Tabla1[Precio Unit. con IVA]) -> 27608 | H10: =Tabla3[[#This Row],[Precio Unit. con IVA]]*Tabla3[[#This Row],[Cantidad Disponible]] -> 0
B11: CRRET36 | C11: Espejo CH Spark GT c/cable LH (10-14) TYC | D11: 1 | E11: =IFERROR(_xlfn.XLOOKUP(Tabla3[[#This Row],[Referencia]], Tabla2[Referencia], Tabla2[Cantidad Vendida]), "0") -> 0 | F11: =Tabla3[[#This Row],[Cantidad]]-Tabla3[[#This Row],[Cantidad Vendida]] -> 1 | G11: =_xlfn.XLOOKUP(Tabla3[[#This Row],[Referencia]],Tabla1[Referencia],Tabla1[Precio Unit. con IVA]) -> 124712 | H11: =Tabla3[[#This Row],[Precio Unit. con IVA]]*Tabla3[[#This Row],[Cantidad Disponible]] -> 124712
B12: CRRET168 | C12: Espejo CH Spark Chronos manual LH (05-14) TYC | D12: 1 | E12: =IFERROR(_xlfn.XLOOKUP(Tabla3[[#This Row],[Referencia]], Tabla2[Referencia], Tabla2[Cantidad Vendida]), "0") -> 0 | F12: =Tabla3[[#This Row],[Cantidad]]-Tabla3[[#This Row],[Cantidad Vendida]] -> 1 | G12: =_xlfn.XLOOKUP(Tabla3[[#This Row],[Referencia]],Tabla1[Referencia],Tabla1[Precio Unit. con IVA]) -> 86632 | H12: =Tabla3[[#This Row],[Precio Unit. con IVA]]*Tabla3[[#This Row],[Cantidad Disponible]] -> 86632
B13: CRRET106 | C13: Espejo CH Corsa c/cable RH (96-04) TYC | D13: 1 | E13: =IFERROR(_xlfn.XLOOKUP(Tabla3[[#This Row],[Referencia]], Tabla2[Referencia], Tabla2[Cantidad Vendida]), "0") -> 0 | F13: =Tabla3[[#This Row],[Cantidad]]-Tabla3[[#This Row],[Cantidad Vendida]] -> 1 | G13: =_xlfn.XLOOKUP(Tabla3[[#This Row],[Referencia]],Tabla1[Referencia],Tabla1[Precio Unit. con IVA]) -> 37128 | H13: =Tabla3[[#This Row],[Precio Unit. con IVA]]*Tabla3[[#This Row],[Cantidad Disponible]] -> 37128
B14: CRRET107 | C14: Espejo CH Corsa c/cable LH (96-04) TYC | D14: 1 | E14: =IFERROR(_xlfn.XLOOKUP(Tabla3[[#This Row],[Referencia]], Tabla2[Referencia], Tabla2[Cantidad Vendida]), "0") -> 0 | F14: =Tabla3[[#This Row],[Cantidad]]-Tabla3[[#This Row],[Cantidad Vendida]] -> 1 | G14: =_xlfn.XLOOKUP(Tabla3[[#This Row],[Referencia]],Tabla1[Referencia],Tabla1[Precio Unit. con IVA]) -> 37128 | H14: =Tabla3[[#This Row],[Precio Unit. con IVA]]*Tabla3[[#This Row],[Cantidad Disponible]] -> 37128
B15: CRSIL10 | C15: Lámpara guardabarro HY Atos LH-RH (05-12) Todo | D15: 6 | E15: =IFERROR(_xlfn.XLOOKUP(Tabla3[[#This Row],[Referencia]], Tabla2[Referencia], Tabla2[Cantidad Vendida]), "0") -> 0 | F15: =Tabla3[[#This Row],[Cantidad]]-Tabla3[[#This Row],[Cantidad Vendida]] -> 6 | G15: =_xlfn.XLOOKUP(Tabla3[[#This Row],[Referencia]],Tabla1[Referencia],Tabla1[Precio Unit. con IVA]) -> 6664 | H15: =Tabla3[[#This Row],[Precio Unit. con IVA]]*Tabla3[[#This Row],[Cantidad Disponible]] -> 39984
B16: CRSIL33 | C16: Lámpara guardabarro CH Spark Chronos c/u LH-RH (05-14) Todo | D16: 6 | E16: =IFERROR(_xlfn.XLOOKUP(Tabla3[[#This Row],[Referencia]], Tabla2[Referencia], Tabla2[Cantidad Vendida]), "0") -> 0 | F16: =Tabla3[[#This Row],[Cantidad]]-Tabla3[[#This Row],[Cantidad Vendida]] -> 6 | G16: =_xlfn.XLOOKUP(Tabla3[[#This Row],[Referencia]],Tabla1[Referencia],Tabla1[Precio Unit. con IVA]) -> 6664 | H16: =Tabla3[[#This Row],[Precio Unit. con IVA]]*Tabla3[[#This Row],[Cantidad Disponible]] -> 39984
... B27: CRREB51 | C27: Bomper trasero HY Grand i10 HB (15-18) FPI | D27: 1 | E27: =IFERROR(_xlfn.XLOOKUP(Tabla3[[#This Row],[Referencia]], Tabla2[Referencia], Tabla2[Cantidad Vendida]), "0") -> 1 | F27: =Tabla3[[#This Row],[Cantidad]]-Tabla3[[#This Row],[Cantidad Vendida]] -> 0 | G27: =_xlfn.XLOOKUP(Tabla3[[#This Row],[Referencia]],Tabla1[Referencia],Tabla1[Precio Unit. con IVA]) -> 197337.7 | H27: =Tabla3[[#This Row],[Precio Unit. con IVA]]*Tabla3[[#This Row],[Cantidad Disponible]] -> 0
D28: =SUM(Tabla3[Cantidad]) -> 52 | E28: =SUM(Tabla3[Cantidad Vendida]) -> 8 | F28: =SUM(Tabla3[Cantidad Disponible]) -> 44 | H28: =SUM(Tabla3[Valor Total con IVA]) -> 1153824
